{"name":"朴素贝叶斯","postlist":[{"title":"基于贝叶斯决策理论的分类方法","slug":"基于概率论的分类方法-朴素贝叶斯","date":"2020-12-24T14:19:00.000Z","updated":"2022-09-30T06:56:37.192Z","comments":true,"path":"api/articles/基于概率论的分类方法-朴素贝叶斯.json","excerpt":null,"keywords":null,"cover":"/.top//attachment:e36f25cc-1cec-4995-809d-c7812f629c99.png","content":null,"raw":null,"categories":[{"name":"Artificial Intelligence","path":"api/categories/Artificial Intelligence.json"},{"name":"Machine Learning","path":"api/categories/Machine Learning.json"},{"name":"Algorithm","path":"api/categories/Algorithm.json"}],"tags":[{"name":"Machine Learning","path":"api/tags/Machine Learning.json"},{"name":"Algorithm","path":"api/tags/Algorithm.json"},{"name":"朴素贝叶斯","path":"api/tags/朴素贝叶斯.json"}]},{"title":"案例-基于朴素贝叶斯过滤垃圾邮件","slug":"案例-基于朴素贝叶斯过滤垃圾邮件","date":"2020-12-25T14:19:00.000Z","updated":"2022-09-30T06:56:37.200Z","comments":true,"path":"api/articles/案例-基于朴素贝叶斯过滤垃圾邮件.json","excerpt":null,"keywords":null,"cover":"https://oceaneyes.top/img/zhishigroup.jpg","content":null,"raw":null,"categories":[{"name":"Artificial Intelligence","path":"api/categories/Artificial Intelligence.json"},{"name":"Machine Learning","path":"api/categories/Machine Learning.json"},{"name":"Algorithm","path":"api/categories/Algorithm.json"}],"tags":[{"name":"Machine Learning","path":"api/tags/Machine Learning.json"},{"name":"Algorithm","path":"api/tags/Algorithm.json"},{"name":"朴素贝叶斯","path":"api/tags/朴素贝叶斯.json"}]}]}